.gitignore
.hgignore
CHANGELOG.rst
COPYRIGHT.txt
MANIFEST.in
README.txt
RELEASE_PROCESS.txt
setup.py
tempitification.sh
FormAlchemy.egg-info/PKG-INFO
FormAlchemy.egg-info/SOURCES.txt
FormAlchemy.egg-info/dependency_links.txt
FormAlchemy.egg-info/entry_points.txt
FormAlchemy.egg-info/not-zip-safe
FormAlchemy.egg-info/requires.txt
FormAlchemy.egg-info/top_level.txt
docs/FormAlchemy.pdf
docs/config.txt
docs/customisation.txt
docs/doc.txt
docs/example-grid.png
docs/example.png
docs/fields.txt
docs/formalchemy.txt
docs/forms.txt
docs/index.txt
docs/internationalisation.txt
docs/models.txt
docs/pylons_sample.txt
docs/tables.txt
docs/templates.txt
docs/validators.txt
docs/ext/admin-listing.png
docs/ext/admin-models.png
docs/ext/admin-new.png
docs/ext/couchdb.txt
docs/ext/fsblob.txt
docs/ext/pylons.txt
docs/ext/rdf.txt
docs/ext/zope.txt
formalchemy/__init__.py
formalchemy/base.py
formalchemy/config.py
formalchemy/exceptions.py
formalchemy/fatypes.py
formalchemy/fields.py
formalchemy/fieldset.tmpl
formalchemy/fieldset_readonly.tmpl
formalchemy/forms.py
formalchemy/grid.tmpl
formalchemy/grid_readonly.tmpl
formalchemy/helpers.py
formalchemy/i18n.py
formalchemy/msgfmt.py
formalchemy/multidict.py
formalchemy/tables.py
formalchemy/templates.py
formalchemy/validators.py
formalchemy/ext/__init__.py
formalchemy/ext/couchdb.py
formalchemy/ext/fsblob.py
formalchemy/ext/rdf.py
formalchemy/ext/pylons/__init__.py
formalchemy/ext/pylons/admin.py
formalchemy/ext/pylons/admin_edit.mako
formalchemy/ext/pylons/admin_index.mako
formalchemy/ext/pylons/admin_list.mako
formalchemy/ext/pylons/base.mako
formalchemy/ext/pylons/controller.py
formalchemy/ext/pylons/maps.py
formalchemy/ext/pylons/pastertemplate.py
formalchemy/ext/pylons/resources/add.png
formalchemy/ext/pylons/resources/admin.css
formalchemy/ext/pylons/resources/delete.png
formalchemy/ext/pylons/resources/edit.png
formalchemy/ext/zope/__init__.py
formalchemy/i18n_resources/formalchemy.pot
formalchemy/i18n_resources/de/LC_MESSAGES/formalchemy.mo
formalchemy/i18n_resources/de/LC_MESSAGES/formalchemy.po
formalchemy/i18n_resources/en/LC_MESSAGES/formalchemy.mo
formalchemy/i18n_resources/en/LC_MESSAGES/formalchemy.po
formalchemy/i18n_resources/es/LC_MESSAGES/formalchemy.mo
