Metadata-Version: 1.1
Name: FormAlchemy
Version: 1.5.6
Summary: FormAlchemy greatly speeds development with SQLAlchemy mapped classes (models) in a HTML forms environment.
Home-page: https://github.com/FormAlchemy/formalchemy
Author: Alexandre Conrad, Jonathan Ellis, Gaël Pasgrimaud, Matthias Urlichs
Author-email: formalchemy@googlegroups.com
License: MIT License
Platform: UNKNOWN
Classifier: Development Status :: 5 - Production/Stable
Classifier: Intended Audience :: Developers
Classifier: License :: OSI Approved :: MIT License
Classifier: Natural Language :: English
Classifier: Operating System :: OS Independent
Classifier: Programming Language :: Python
Classifier: Topic :: Software Development :: Libraries :: Python Modules
Classifier: Topic :: Software Development :: User Interfaces
Classifier: Topic :: Text Processing :: Markup :: HTML
Classifier: Topic :: Utilities
